class_task/week1/param_alu/alu.v

module alu #(
   parameter IN_DATA_W_1 = 18,
   IN_DATA_W_2 = 48,
   OUT_DATA_W = 48 
) (a, b,c,d,carryin, select, P,clk);
input [IN_DATA_W_1-1:0] a, b, d;
input [IN_DATA_W_2-1:0] c;
input carryin,clk;
input [1:0] select;
output reg [OUT_DATA_W-1:0]P;

//generate
    
if(OUT_DATA_W > 2*IN_DATA_W_2) begin
    always @(posedge clk) 
    begin
    
    case (select)
    2'b00 : P = ~((a|b)&d);//2-1 AOI gate
    2'b01 : P = (a*b)+d+carryin;
    2'b10 : P = ~c;
    2'b11 : P = c-a-b-d-carryin;	
          
    endcase
    end
        
end
else begin
    always @(posedge clk) 
    begin
    
    case (select)
    2'b00 : P = ~((a|b)&d);//2-1 AOI gate
    2'b01 : P = a+b+d+carryin;
    2'b10 : P = ~c;
    2'b11 : P = ~(c&a&b&d);	
          
    endcase
    end
end

//endgenerate

endmodule

class_task/week1/param_alu/tb.v
`timescale 1ns/1ps
module tb;
    reg [17:0]a,b,d;
    reg clk,carryin;
    reg [1:0]select;
    reg [47:0]c;
    wire [47:0]P;

    alu #(.IN_DATA_W_1(18), .IN_DATA_W_2(48), .OUT_DATA_W (48) ) DUT(a, b,c,d,carryin, select, P,clk);

    initial begin
        clk = 1'b0;
        forever begin
            #5 clk = ~clk;
        end
    end

    integer i;

    initial begin
        $dumpfile("alu.vcd");
        $dumpvars(0,tb);
        carryin = 1'b1;
        a  = 18'h12345;
        b = 18'h23456;
        d = 18'h34567;
        c = 48'h456789ABCDEF;
        
        for(i=0;i<4;i=i+1) begin
            select = i;
            #10;
        end
        #10
        $finish;
    end

    initial $monitor($time," a = %h , b = %h, c = %h, d = %h, carryin = %b, sel = %b, P = %h",a,b,c,d,carryin,select,P);

endmodule

class_task/week1/param_alu/alu.vcd
$date
	Fri Aug 11 05:53:28 2023
$end
$version
	Icarus Verilog
$end
$timescale
	1ps
$end
$scope module tb $end
$var wire 48 ! P [47:0] $end
$var reg 18 " a [17:0] $end
$var reg 18 # b [17:0] $end
$var reg 48 $ c [47:0] $end
$var reg 1 % carryin $end
$var reg 1 & clk $end
$var reg 18 ' d [17:0] $end
$var reg 2 ( select [1:0] $end
$var integer 32 ) i [31:0] $end
$scope module DUT $end
$var wire 18 * a [17:0] $end
$var wire 18 + b [17:0] $end
$var wire 48 , c [47:0] $end
$var wire 1 % carryin $end
$var wire 1 & clk $end
$var wire 18 - d [17:0] $end
$var wire 2 . select [1:0] $end
$var reg 48 / P [47:0] $end
$scope begin genblk2 $end
$upscope $end
$upscope $end
$upscope $end
$enddefinitions $end
#0
$dumpvars
bx /
b0 .
b110100010101100111 -
b10001010110011110001001101010111100110111101111 ,
b100011010001010110 +
b10010001101000101 *
b0 )
b0 (
b110100010101100111 '
0&
1%
b10001010110011110001001101010111100110111101111 $
b100011010001010110 #
b10010001101000101 "
bx !
$end
#5000
b111111111111111111111111111111001111101010111000 !
b111111111111111111111111111111001111101010111000 /
1&
#10000
0&
b1 (
b1 .
b1 )
#15000
b1101001110100000011 !
b1101001110100000011 /
1&
#20000
0&
b10 (
b10 .
b10 )
#25000
b101110101001100001110110010101000011001000010000 !
b101110101001100001110110010101000011001000010000 /
1&
#30000
0&
b11 (
b11 .
b11 )
#35000
b111111111111111111111111111111111111111110111011 !
b111111111111111111111111111111111111111110111011 /
1&
#40000
0&
b100 )
